Athira_odd_or_even/__init__.py
athira_odd_or_even-0.1.0.dist-info/licenses/LICENSE
athira_odd_or_even-0.1.0.dist-info/METADATA
athira_odd_or_even-0.1.0.dist-info/WHEEL
athira_odd_or_even-0.1.0.dist-info/top_level.txt
athira_odd_or_even-0.1.0.dist-info/RECORD
