Metadata-Version: 2.4
Name: Athira_odd_or_even
Version: 0.1.0
Summary: A simple Python package to check odd or even numbers
License-File: LICENSE
Dynamic: license-file
